Concurrent_AP.py
README
setup.py
Concurrent_AP.egg-info/PKG-INFO
Concurrent_AP.egg-info/SOURCES.txt
Concurrent_AP.egg-info/dependency_links.txt
Concurrent_AP.egg-info/entry_points.txt
Concurrent_AP.egg-info/requires.txt
Concurrent_AP.egg-info/top_level.txt