Metadata-Version: 1.1
Name: Concurrent-AP
Version: 1.4
Summary: Scalable and parallel programming implementation of Affinity Propagation clustering
Home-page: https://github.com/GGiecold/Concurrent_AP
Author: Gregory Giecold
Author-email: ggiecold@jimmy.harvard.edu
License: MIT License
Download-URL: https://github.com/GGiecold/Concurrent_AP
Keywords: parallel multiprocessing machine-learning concurrent clustering
Platform: Any
Classifier: Development Status :: 4 - Beta
Classifier: Environment :: Console
Classifier: Intended Audience :: End Users/Desktop
Classifier: Intended Audience :: Developers
Classifier: Intended Audience :: Science/Research
Classifier: License :: OSI Approved :: MIT License
Classifier: Natural Language :: English
Classifier: Operating System :: MacOS :: MacOS X
Classifier: Operating System :: POSIX
Classifier: Programming Language :: Python :: 2.7
Classifier: Topic :: Scientific/Engineering
Classifier: Topic :: Scientific/Engineering :: Visualization
Classifier: Topic :: Scientific/Engineering :: Mathematics
